django_autocomplete/__init__.py
django_autocomplete/apps.py
django_autocomplete/models.py
django_autocomplete/utils.py
django_autocomplete/migrations/__init__.py
django_autocomplete_plugin-0.1.0.dist-info/METADATA
django_autocomplete_plugin-0.1.0.dist-info/WHEEL
django_autocomplete_plugin-0.1.0.dist-info/top_level.txt
django_autocomplete_plugin-0.1.0.dist-info/RECORD
