Metadata-Version: 2.4
Name: django-autocomplete-plugin
Version: 0.1.0
Summary: Django autocomplete plugin for VS Code
Home-page: https://github.com/yourusername/django-autocomplete-plugin
Author: Your Name
Author-email: your.email@example.com
Classifier: Framework :: Django
Classifier: Programming Language :: Python :: 3
Classifier: Operating System :: OS Independent
Requires-Dist: Django>=3.2
Dynamic: author
Dynamic: author-email
Dynamic: classifier
Dynamic: home-page
Dynamic: requires-dist
Dynamic: summary
